PoseDetector/PoseModule.py
PoseDetector/__init__.py
PoseEstimator-0.0.1.dist-info/METADATA
PoseEstimator-0.0.1.dist-info/WHEEL
PoseEstimator-0.0.1.dist-info/top_level.txt
PoseEstimator-0.0.1.dist-info/RECORD
