Metadata-Version: 2.1
Name: PoseEstimator
Version: 0.0.1
Summary: Basic Pose estimation Module
Home-page: UNKNOWN
Author: Syed Abdul Gaffar Shakhadri
Author-email: <syed.17.beec@acharya.ac.in>
License: UNKNOWN
Keywords: python,pose,pose-estimation,Pose Estimation,opencv pose estimation,estimation
Platform: UNKNOWN
Classifier: Development Status :: 1 - Planning
Classifier: Intended Audience :: Developers
Classifier: Programming Language :: Python :: 3
Classifier: Operating System :: Unix
Classifier: Operating System :: MacOS :: MacOS X
Classifier: Operating System :: Microsoft :: Windows
Requires-Dist: opencv-python
Requires-Dist: mediapipe
